claude_pyhooks/__init__.py
claude_pyhooks/py.typed
claude_pyhooks/commands/__init__.py
claude_pyhooks/commands/audio.py
claude_pyhooks/commands/output_base.py
claude_pyhooks/commands/outputs.py
claude_pyhooks/commands/queue.py
claude_pyhooks/inputs/__init__.py
claude_pyhooks/inputs/base.py
claude_pyhooks/inputs/hook_input.py
claude_pyhooks/inputs/responses.py
claude_pyhooks/inputs/tools.py
claude_pyhooks/utils/__init__.py
claude_pyhooks/utils/json_element.py
claude_pyhooks-0.1.1.dist-info/METADATA
claude_pyhooks-0.1.1.dist-info/WHEEL
claude_pyhooks-0.1.1.dist-info/licenses/LICENSE
claude_pyhooks-0.1.1.dist-info/RECORD
