Metadata-Version: 2.4
Name: claude-pyhooks
Version: 0.1.1
Summary: A lightweight framework for implementing Claude Code hooks in Python.
Project-URL: Homepage, https://github.com/kakune/claude-pyhooks
Project-URL: Repository, https://github.com/kakune/claude-pyhooks
Project-URL: Issues, https://github.com/kakune/claude-pyhooks/issues
Author-email: kakune <kak.r.1729@gmail.com>
License: MIT License
License-File: LICENSE
Keywords: automation,claude,cli,framework,hooks
Classifier: Development Status :: 4 - Beta
Classifier: Intended Audience :: Developers
Classifier: License :: OSI Approved :: MIT License
Classifier: Operating System :: OS Independent
Classifier: Programming Language :: Python :: 3
Classifier: Programming Language :: Python :: 3.12
Classifier: Programming Language :: Python :: 3.13
Classifier: Topic :: Software Development :: Libraries :: Python Modules
Classifier: Topic :: System :: Shells
Requires-Python: >=3.12
